jtokengen/__init__.py
jtokengen/main.py
jtokengen-0.0.4.data/scripts/jtokengen
jtokengen-0.0.4.dist-info/METADATA
jtokengen-0.0.4.dist-info/WHEEL
jtokengen-0.0.4.dist-info/top_level.txt
jtokengen-0.0.4.dist-info/RECORD
