Metadata-Version: 2.1
Name: jtokengen
Version: 0.0.4
Summary: Easier command token generator.
Home-page: https://github.com/jumichica/tokengen
Author: Edwin Ariza
Author-email: me@edwinariza.com
License: MIT
Platform: UNKNOWN
Classifier: Development Status :: 1 - Planning
Classifier: Intended Audience :: Science/Research
Classifier: License :: OSI Approved :: BSD License
Classifier: Operating System :: POSIX :: Linux
Classifier: Programming Language :: Python :: 2
Classifier: Programming Language :: Python :: 2.7
Classifier: Programming Language :: Python :: 3
Classifier: Programming Language :: Python :: 3.4
Classifier: Programming Language :: Python :: 3.5
